{
  "version": 1,
  "active": false,
  "skill": "ralplan",
  "keyword": "$ralplan",
  "phase": "complete",
  "activated_at": "2026-04-11T03:04:22.062Z",
  "updated_at": "2026-04-11T03:10:33.854Z",
  "source": "keyword-detector",
  "session_id": "019d7a84-befc-7f63-bd95-eb51706a975f",
  "turn_id": "019d7a84-bf29-7ce2-90ea-a92f701cb18f",
  "active_skills": [],
  "initialized_mode": "ralplan",
  "initialized_state_path": ".omx/state/sessions/019d7a84-befc-7f63-bd95-eb51706a975f/ralplan-state.json"
}